nekro_agent/__init__.py
nekro_agent/__init__post.py
nekro_agent/adapters/__init__.py
nekro_agent/adapters/utils.py
nekro_agent/adapters/bilibili_live/README.md
nekro_agent/adapters/bilibili_live/__init__.py
nekro_agent/adapters/bilibili_live/adapter.py
nekro_agent/adapters/bilibili_live/core/client.py
nekro_agent/adapters/bilibili_live/templates/practice.j2
nekro_agent/adapters/bilibili_live/templates/practice.py
nekro_agent/adapters/discord/README.md
nekro_agent/adapters/discord/__init__.py
nekro_agent/adapters/discord/adapter.py
nekro_agent/adapters/discord/client.py
nekro_agent/adapters/discord/config.py
nekro_agent/adapters/discord/tools.py
nekro_agent/adapters/email/README.md
nekro_agent/adapters/email/__init__.py
nekro_agent/adapters/email/adapter.py
nekro_agent/adapters/email/base.py
nekro_agent/adapters/email/config.py
nekro_agent/adapters/email/routers.py
nekro_agent/adapters/interface/__init__.py
nekro_agent/adapters/interface/base.py
nekro_agent/adapters/interface/collector.py
nekro_agent/adapters/interface/convertor.py
nekro_agent/adapters/interface/schemas/extra.py
nekro_agent/adapters/interface/schemas/platform.py
nekro_agent/adapters/minecraft/README.md
nekro_agent/adapters/minecraft/__init__.py
nekro_agent/adapters/minecraft/adapter.py
nekro_agent/adapters/minecraft/core/bot.py
nekro_agent/adapters/minecraft/matchers/message.py
nekro_agent/adapters/minecraft/matchers/notice.py
nekro_agent/adapters/minecraft/tools/__init__.py
nekro_agent/adapters/onebot_v11/README.md
nekro_agent/adapters/onebot_v11/__init__.py
nekro_agent/adapters/onebot_v11/adapter.py
nekro_agent/adapters/onebot_v11/routers.py
nekro_agent/adapters/onebot_v11/core/bot.py
nekro_agent/adapters/onebot_v11/matchers/__init__.py
nekro_agent/adapters/onebot_v11/matchers/command.py
nekro_agent/adapters/onebot_v11/matchers/guard.py
nekro_agent/adapters/onebot_v11/matchers/message.py
nekro_agent/adapters/onebot_v11/matchers/notice.py
nekro_agent/adapters/onebot_v11/tools/at_parser.py
nekro_agent-2.2.0.dist-info/METADATA
nekro_agent-2.2.0.dist-info/WHEEL
nekro_agent-2.2.0.dist-info/entry_points.txt
nekro_agent-2.2.0.dist-info/licenses/LICENSE
nekro_agent-2.2.0.dist-info/RECORD
