Metadata-Version: 2.4
Name: nekro-agent
Version: 2.2.0
Summary: 更智能、更优雅的代理执行 AI
Project-URL: Homepage, https://github.com/KroMiose/nekro-agent
Project-URL: Repository, https://github.com/KroMiose/nekro-agent
Author-email: KroMiose <li_xiangff@163.com>
License: Custom License
License-File: LICENSE
Keywords: agent,ai,nonebot
Classifier: Programming Language :: Python :: 3.11
Classifier: Programming Language :: Python :: 3.12
Requires-Python: <3.13,>=3.11
Requires-Dist: aiodocker<1.0.0,>=0.22.2
Requires-Dist: aiofiles<25.0.0,>=24.1.0
Requires-Dist: aiohttp<4.0.0,>=3.11.15
Requires-Dist: aiosmtplib<3.0.0,>=2.0.0
Requires-Dist: asyncpg<1.0.0,>=0.30.0
Requires-Dist: bcrypt<5.0.0,>=4.2.0
Requires-Dist: discord-py<3.0.0,>=2.5.2
Requires-Dist: docker<8.0.0,>=7.1.0
Requires-Dist: gitpython<4.0.0,>=3.1.44
Requires-Dist: httpx[socks]<0.28.0,>=0.27.0
Requires-Dist: json5<1.0.0,>=0.10.0
Requires-Dist: lunar-python<2.0.0,>=1.3.12
Requires-Dist: matplotlib<4.0.0,>=3.10.3
Requires-Dist: mcp<2.0.0,>=1.7.0
Requires-Dist: mem0ai<1.0.0,>=0.1.79
Requires-Dist: nonebot-adapter-minecraft<1.5,>=1.4.0
Requires-Dist: nonebot-adapter-onebot<3.0.0,>=2.4.2
Requires-Dist: nonebot2[fastapi]<3.0.0,>=2.2.1
Requires-Dist: openai<1.108.0,>=1.107.0
Requires-Dist: openpyxl<4.0.0,>=3.1.2
Requires-Dist: pandas<3.0.0,>=2.3.0
Requires-Dist: passlib[bcrypt]<2.0.0,>=1.7.4
Requires-Dist: pillow<11.0.0,>=10.4.0
Requires-Dist: pip>=24.0
Requires-Dist: psutil<8.0.0,>=7.0.0
Requires-Dist: psycopg2-binary<3.0.0,>=2.9.9
Requires-Dist: pycryptodome<4.0.0,>=3.23.0
Requires-Dist: python-jose[cryptography]<4.0.0,>=3.3.0
Requires-Dist: python-magic-bin<1.0.0,>=0.4.14; sys_platform == 'win32'
Requires-Dist: python-magic<1.0.0,>=0.4.27
Requires-Dist: python-multipart<1.0.0,>=0.0.9
Requires-Dist: python-telegram-bot<23.0,>=22.4
Requires-Dist: qdrant-client<1.16.0,>=1.15.0
Requires-Dist: sse-starlette<3.0.0,>=2.2.1
Requires-Dist: tiktoken<1.0.0,>=0.7.0
Requires-Dist: toml<1.0.0,>=0.10.2
Requires-Dist: tortoise-orm==0.24
Requires-Dist: tzlocal<6.0,>=5.2
Requires-Dist: weave<1.0.0,>=0.51.19
Requires-Dist: websockets<16.0.0,>=15.0.1
Provides-Extra: dev
Requires-Dist: nb-cli<2.0.0,>=1.4.0; extra == 'dev'
Requires-Dist: poethepoet<1.0.0,>=0.24.0; extra == 'dev'
Requires-Dist: ruff<1.0.0,>=0.14.10; extra == 'dev'
Requires-Dist: uvicorn<1.0.0,>=0.23.2; extra == 'dev'
